LICENSE
MANIFEST.in
README.md
build_libpg_query.sh
setup.py
psqlparse/__init__.py
psqlparse/exceptions.py
psqlparse/nodes.py
psqlparse/parser.c
psqlparse/parser.pyx
psqlparse/pg_query.pxd
psqlparse.egg-info/PKG-INFO
psqlparse.egg-info/SOURCES.txt
psqlparse.egg-info/dependency_links.txt
psqlparse.egg-info/requires.txt
psqlparse.egg-info/top_level.txt
test/test_parse.py