Metadata-Version: 1.0
Name: psqlparse
Version: 0.2.5
Summary: Parse SQL queries using the PostgreSQL query parser
Home-page: https://github.com/alculquicondor/psqlparse
Author: Aldo Culquicondor
Author-email: aldo@amigocloud.com
License: BSD
Platform: UNKNOWN
